paranet_agent/__init__.py
paranet_agent/actor.py
paranet_agent/composer.py
paranet_agent/connector.py
paranet_agent/decorations.py
paranet_agent/deployment.py
paranet_agent/gql.py
paranet_agent/marshalling.py
paranet_agent/metadata.py
paranet_agent/paraflow.py
paranet_agent/version.py
paranet_agent-2.0.2.dist-info/METADATA
paranet_agent-2.0.2.dist-info/WHEEL
paranet_agent-2.0.2.dist-info/RECORD
