Metadata-Version: 2.4
Name: paranet_agent
Version: 2.0.2
Summary: Paranet Agent SDK
Author: Otonoma
License: MIT
Classifier: License :: OSI Approved :: MIT License
Classifier: Operating System :: OS Independent
Classifier: Programming Language :: Python :: 3
Requires-Python: >=3.8
Requires-Dist: aiohttp
Requires-Dist: python-on-whales
Requires-Dist: pyyaml
Requires-Dist: requests
Requires-Dist: strawberry-graphql
